{"title":"优秀软件推荐","uid":"afeb238b4e43dc74ed7b3b1b959d6805","slug":"优秀软件推荐","date":"2025-06-29T05:22:57.000Z","updated":"2025-06-29T05:24:18.180Z","comments":true,"path":"api/articles/优秀软件推荐.json","keywords":"编程 日常 游戏","cover":[],"content":"<h1 id=\"优秀软件推荐\"><a href=\"#优秀软件推荐\" class=\"headerlink\" title=\"优秀软件推荐\"></a>优秀软件推荐</h1><p><strong>如无特殊说明，默认仅支持 Windows。“免费”指基本功能，如有收费内容会说明。“连接快”指任一下载页面访问快。（如经常断连则不会勾选）</strong></p>\n<p><mark><em><strong><u>本帖并无任何打广告行为，我没有收到任何钱，给出的一切购买图片只是让你参考看看！！！</u></strong></em></mark></p>\n<h2 id=\"强烈推荐\"><a href=\"#强烈推荐\" class=\"headerlink\" title=\"强烈推荐\"></a>强烈推荐</h2><h3 id=\"163MusicLyrics\"><a href=\"#163MusicLyrics\" class=\"headerlink\" title=\"163MusicLyrics\"></a>163MusicLyrics</h3><p>仓库：<a href=\"https://github.com/jitwxs/163MusicLyrics\">https://github.com/jitwxs/163MusicLyrics</a> </p>\n<ul>\n<li><p><input checked=\"\" disabled=\"\" type=\"checkbox\"> \n免安装</p>\n</li>\n<li><p><input checked=\"\" disabled=\"\" type=\"checkbox\"> \n开源</p>\n</li>\n<li><p><input disabled=\"\" type=\"checkbox\"> \n有官网</p>\n</li>\n<li><p><input disabled=\"\" type=\"checkbox\"> \n连接快</p>\n</li>\n<li><p><input checked=\"\" disabled=\"\" type=\"checkbox\"> \n免费</p>\n</li>\n<li><p><input checked=\"\" disabled=\"\" type=\"checkbox\"> \n操作简单</p>\n</li>\n<li><p><input checked=\"\" disabled=\"\" type=\"checkbox\"> \n中文支持</p>\n</li>\n</ul>\n<p>这是一个可以获取网易云音乐的歌词的软件，网页版网易云音乐的播放页面链接为 <a href=\"https://music.163.com/#/song?id=xxx\">https://music.163.com/#/song?id=xxx</a> ，其中 <code>xxx</code> 是音乐的编号，在软件的输入框中输入即可获取歌词。</p>\n<p><img src=\"/assets/%E4%BC%98%E7%A7%80%E8%BD%AF%E4%BB%B6%E6%8E%A8%E8%8D%90/img0.png\"></p>\n<h3 id=\"ApkShellext2\"><a href=\"#ApkShellext2\" class=\"headerlink\" title=\"ApkShellext2\"></a>ApkShellext2</h3><p>官网：<a href=\"http://www.apkshellext.com/\">http://www.apkshellext.com/</a> </p>\n<p>仓库：<a href=\"https://github.com/kkguo/apkshellext\">https://github.com/kkguo/apkshellext</a> </p>\n<ul>\n<li><p><input checked=\"\" disabled=\"\" type=\"checkbox\"> \n免安装</p>\n</li>\n<li><p><input checked=\"\" disabled=\"\" type=\"checkbox\"> \n开源</p>\n</li>\n<li><p><input checked=\"\" disabled=\"\" type=\"checkbox\"> \n有官网</p>\n</li>\n<li><p><input disabled=\"\" type=\"checkbox\"> \n连接快</p>\n</li>\n<li><p><input checked=\"\" disabled=\"\" type=\"checkbox\"> \n免费</p>\n</li>\n<li><p><input checked=\"\" disabled=\"\" type=\"checkbox\"> \n操作简单</p>\n</li>\n<li><p><input disabled=\"\" type=\"checkbox\"> \n中文支持</p>\n</li>\n</ul>\n<p>这个软件可以让你能够在文件资源管理器中预览安卓应用（apk）图标。运行 <code>install.bat</code> 即可生效。</p>\n<h3 id=\"Bandicam\"><a href=\"#Bandicam\" class=\"headerlink\" title=\"Bandicam\"></a>Bandicam</h3><p>官网：<a href=\"https://www.bandicam.cn/\">https://www.bandicam.cn/</a> </p>\n<ul>\n<li><p><input disabled=\"\" type=\"checkbox\"> \n免安装</p>\n</li>\n<li><p><input disabled=\"\" type=\"checkbox\"> \n开源</p>\n</li>\n<li><p><input checked=\"\" disabled=\"\" type=\"checkbox\"> \n有官网</p>\n</li>\n<li><p><input checked=\"\" disabled=\"\" type=\"checkbox\"> \n连接快</p>\n</li>\n<li><p><input checked=\"\" disabled=\"\" type=\"checkbox\"> \n免费</p>\n</li>\n<li><p><input checked=\"\" disabled=\"\" type=\"checkbox\"> \n操作简单</p>\n</li>\n<li><p><input checked=\"\" disabled=\"\" type=\"checkbox\"> \n中文支持</p>\n</li>\n</ul>\n<p><strong>大量功能需付费。</strong></p>\n<p><img src=\"/assets/%E4%BC%98%E7%A7%80%E8%BD%AF%E4%BB%B6%E6%8E%A8%E8%8D%90/img2.png\"></p>\n<p>一个知名的强大的录屏软件。</p>\n<p><img src=\"/assets/%E4%BC%98%E7%A7%80%E8%BD%AF%E4%BB%B6%E6%8E%A8%E8%8D%90/img1.png\"></p>\n<h3 id=\"DirectX-Repair\"><a href=\"#DirectX-Repair\" class=\"headerlink\" title=\"DirectX_Repair\"></a>DirectX_Repair</h3><p>官网：<a href=\"https://www.zysoftware.top/post/9.html\">https://www.zysoftware.top/post/9.html</a> </p>\n<ul>\n<li><p><input checked=\"\" disabled=\"\" type=\"checkbox\"> \n免安装</p>\n</li>\n<li><p><input disabled=\"\" type=\"checkbox\"> \n开源</p>\n</li>\n<li><p><input checked=\"\" disabled=\"\" type=\"checkbox\"> \n有官网</p>\n</li>\n<li><p><input checked=\"\" disabled=\"\" type=\"checkbox\"> \n连接快</p>\n</li>\n<li><p><input checked=\"\" disabled=\"\" type=\"checkbox\"> \n免费</p>\n</li>\n<li><p><input checked=\"\" disabled=\"\" type=\"checkbox\"> \n操作简单</p>\n</li>\n<li><p><input checked=\"\" disabled=\"\" type=\"checkbox\"> \n中文支持</p>\n</li>\n</ul>\n<p>这个软件可以解决玩游戏（也包括一些其他软件）的一些报错，当你误将“Microsoft”认成“Minecraft”并卸载了某个个 VC++ 运行库（我一个朋友）时，也可以使用这个软件来修复。</p>\n<p><img src=\"/assets/%E4%BC%98%E7%A7%80%E8%BD%AF%E4%BB%B6%E6%8E%A8%E8%8D%90/img3.png\"></p>\n<h3 id=\"MarkText\"><a href=\"#MarkText\" class=\"headerlink\" title=\"MarkText\"></a>MarkText</h3><p>官网：<a href=\"https://www.marktext.cc/\">https://www.marktext.cc/</a> </p>\n<p>汉化版（社区）：<a href=\"https://marktext.weero.net/\">https://marktext.weero.net/</a> </p>\n<p>仓库：<a href=\"https://github.com/marktext/marktext\">https://github.com/marktext/marktext</a> </p>\n<p>汉化版（社区）仓库：<a href=\"https://github.com/topabomb/marktext-specialedition\">https://github.com/topabomb/marktext-specialedition</a> </p>\n<p>支持 MacOS, Linux</p>\n<ul>\n<li><p><input checked=\"\" disabled=\"\" type=\"checkbox\"> \n免安装</p>\n</li>\n<li><p><input checked=\"\" disabled=\"\" type=\"checkbox\"> \n开源</p>\n</li>\n<li><p><input checked=\"\" disabled=\"\" type=\"checkbox\"> \n有官网</p>\n</li>\n<li><p><input checked=\"\" disabled=\"\" type=\"checkbox\"> \n连接快</p>\n</li>\n<li><p><input checked=\"\" disabled=\"\" type=\"checkbox\"> \n免费</p>\n</li>\n<li><p><input checked=\"\" disabled=\"\" type=\"checkbox\"> \n操作简单</p>\n</li>\n<li><p><input checked=\"\" disabled=\"\" type=\"checkbox\"> \n中文支持</p>\n</li>\n</ul>\n<p>十分好用的 Markdown 编辑器，支持 Markdown 全部语法，并扩展了一些语法。界面舒适，有 6 种主题，可以像 Word 一样编写文档。性能不太好，这个文档写了一半多的时候很卡（我的CPU: Intel Core i5-3230M, RAM: 4GB，我的电脑性能很差，你应该能多写点），对性能有要求的话可以用 VSCode扩展。</p>\n<p><strong>并没有图片中那么简陋。</strong></p>\n<p><img src=\"/assets/%E4%BC%98%E7%A7%80%E8%BD%AF%E4%BB%B6%E6%8E%A8%E8%8D%90/img7.png\"></p>\n<h3 id=\"noMeiryoUI\"><a href=\"#noMeiryoUI\" class=\"headerlink\" title=\"noMeiryoUI\"></a>noMeiryoUI</h3><p>仓库：<a href=\"https://github.com/Tatsu-syo/noMeiryoUI\">https://github.com/Tatsu-syo/noMeiryoUI</a> </p>\n<ul>\n<li><p><input checked=\"\" disabled=\"\" type=\"checkbox\"> \n免安装</p>\n</li>\n<li><p><input checked=\"\" disabled=\"\" type=\"checkbox\"> \n开源</p>\n</li>\n<li><p><input disabled=\"\" type=\"checkbox\"> \n有官网</p>\n</li>\n<li><p><input disabled=\"\" type=\"checkbox\"> \n连接快</p>\n</li>\n<li><p><input checked=\"\" disabled=\"\" type=\"checkbox\"> \n免费</p>\n</li>\n<li><p><input checked=\"\" disabled=\"\" type=\"checkbox\"> \n操作简单</p>\n</li>\n<li><p><input checked=\"\" disabled=\"\" type=\"checkbox\"> \n中文支持</p>\n</li>\n</ul>\n<p>可以更改系统字体。</p>\n<p><img src=\"/assets/%E4%BC%98%E7%A7%80%E8%BD%AF%E4%BB%B6%E6%8E%A8%E8%8D%90/img8.png\"></p>\n<h3 id=\"Office-Tool\"><a href=\"#Office-Tool\" class=\"headerlink\" title=\"Office Tool\"></a>Office Tool</h3><p>官网：<a href=\"https://otp.landian.vip/zh-cn/\">https://otp.landian.vip/zh-cn/</a> </p>\n<p>仓库：<a href=\"https://github.com/YerongAI/Office-Tool\">https://github.com/YerongAI/Office-Tool</a> </p>\n<ul>\n<li><p><input checked=\"\" disabled=\"\" type=\"checkbox\"> \n免安装</p>\n</li>\n<li><p><input checked=\"\" disabled=\"\" type=\"checkbox\"> \n开源</p>\n</li>\n<li><p><input checked=\"\" disabled=\"\" type=\"checkbox\"> \n有官网</p>\n</li>\n<li><p><input checked=\"\" disabled=\"\" type=\"checkbox\"> \n连接快</p>\n</li>\n<li><p><input checked=\"\" disabled=\"\" type=\"checkbox\"> \n免费</p>\n</li>\n<li><p><input checked=\"\" disabled=\"\" type=\"checkbox\"> \n操作简单</p>\n</li>\n<li><p><input checked=\"\" disabled=\"\" type=\"checkbox\"> \n中文支持</p>\n</li>\n</ul>\n<p>图形化界面快速高自定义部署 Office。</p>\n<p><img src=\"/assets/%E4%BC%98%E7%A7%80%E8%BD%AF%E4%BB%B6%E6%8E%A8%E8%8D%90/img9.png\"></p>\n<p>TODO</p>\n<h3 id=\"QtScrcpy\"><a href=\"#QtScrcpy\" class=\"headerlink\" title=\"QtScrcpy\"></a>QtScrcpy</h3><p>仓库：<a href=\"https://github.com/barry-ran/QtScrcpy\">https://github.com/barry-ran/QtScrcpy</a> </p>\n<p>支持 MacOS, Linux</p>\n<ul>\n<li><p><input checked=\"\" disabled=\"\" type=\"checkbox\"> \n免安装</p>\n</li>\n<li><p><input checked=\"\" disabled=\"\" type=\"checkbox\"> \n开源</p>\n</li>\n<li><p><input disabled=\"\" type=\"checkbox\"> \n有官网</p>\n</li>\n<li><p><input disabled=\"\" type=\"checkbox\"> \n连接快</p>\n</li>\n<li><p><input checked=\"\" disabled=\"\" type=\"checkbox\"> \n免费</p>\n</li>\n<li><p><input checked=\"\" disabled=\"\" type=\"checkbox\"> \n操作简单</p>\n</li>\n<li><p><input checked=\"\" disabled=\"\" type=\"checkbox\"> \n中文支持</p>\n</li>\n</ul>\n<p>安卓投屏到电脑，并可在电脑上控制。性能好，质量高，延迟低，启动快，不需要在手机上安装软件（传输音频除外）。</p>\n<p><img src=\"/assets/%E4%BC%98%E7%A7%80%E8%BD%AF%E4%BB%B6%E6%8E%A8%E8%8D%90/img10.png\"></p>\n<h3 id=\"Windows-右键管理\"><a href=\"#Windows-右键管理\" class=\"headerlink\" title=\"Windows 右键管理\"></a>Windows 右键管理</h3><p>仓库：<a href=\"https://github.com/BluePointLilac/ContextMenuManager\">https://github.com/BluePointLilac/ContextMenuManager</a> </p>\n<ul>\n<li><p><input checked=\"\" disabled=\"\" type=\"checkbox\"> \n免安装</p>\n</li>\n<li><p><input checked=\"\" disabled=\"\" type=\"checkbox\"> \n开源</p>\n</li>\n<li><p><input disabled=\"\" type=\"checkbox\"> \n有官网</p>\n</li>\n<li><p><input disabled=\"\" type=\"checkbox\"> \n连接快</p>\n</li>\n<li><p><input checked=\"\" disabled=\"\" type=\"checkbox\"> \n免费</p>\n</li>\n<li><p><input checked=\"\" disabled=\"\" type=\"checkbox\"> \n操作简单</p>\n</li>\n<li><p><input checked=\"\" disabled=\"\" type=\"checkbox\"> \n中文支持</p>\n</li>\n</ul>\n<p>管理 Windows 的右键菜单</p>\n<p><img src=\"/assets/%E4%BC%98%E7%A7%80%E8%BD%AF%E4%BB%B6%E6%8E%A8%E8%8D%90/img12.png\"></p>\n<h3 id=\"Resourse-Hacker\"><a href=\"#Resourse-Hacker\" class=\"headerlink\" title=\"Resourse Hacker\"></a>Resourse Hacker</h3><ul>\n<li><p><input checked=\"\" disabled=\"\" type=\"checkbox\"> \n免安装</p>\n</li>\n<li><p><input disabled=\"\" type=\"checkbox\"> \n开源</p>\n</li>\n<li><p><input checked=\"\" disabled=\"\" type=\"checkbox\"> \n有官网</p>\n</li>\n<li><p><input checked=\"\" disabled=\"\" type=\"checkbox\"> \n连接快</p>\n</li>\n<li><p><input checked=\"\" disabled=\"\" type=\"checkbox\"> \n免费</p>\n</li>\n<li><p><input checked=\"\" disabled=\"\" type=\"checkbox\"> \n操作简单</p>\n</li>\n<li><p><input disabled=\"\" type=\"checkbox\"> \n中文支持</p>\n</li>\n</ul>\n<p>查看exe, dll等文件的资源（如图标、图像、字符串等资源文件），并可以导出、替换。</p>\n<p><img src=\"/assets/%E4%BC%98%E7%A7%80%E8%BD%AF%E4%BB%B6%E6%8E%A8%E8%8D%90/img13.png\"></p>\n<h3 id=\"Geek-Uninstaller\"><a href=\"#Geek-Uninstaller\" class=\"headerlink\" title=\"Geek Uninstaller\"></a>Geek Uninstaller</h3><p>官网：<a href=\"https://geekuninstaller.com/\">https://geekuninstaller.com/</a> </p>\n<ul>\n<li><p><input checked=\"\" disabled=\"\" type=\"checkbox\"> \n免安装</p>\n</li>\n<li><p><input disabled=\"\" type=\"checkbox\"> \n开源</p>\n</li>\n<li><p><input checked=\"\" disabled=\"\" type=\"checkbox\"> \n有官网</p>\n</li>\n<li><p><input checked=\"\" disabled=\"\" type=\"checkbox\"> \n连接快</p>\n</li>\n<li><p><input checked=\"\" disabled=\"\" type=\"checkbox\"> \n免费</p>\n</li>\n<li><p><input checked=\"\" disabled=\"\" type=\"checkbox\"> \n操作简单</p>\n</li>\n<li><p><input checked=\"\" disabled=\"\" type=\"checkbox\"> \n中文支持</p>\n</li>\n</ul>\n<p>强大的卸载软件，可以清理注册表和文件残留，也能卸载微软商店应用。</p>\n<p><img src=\"/assets/%E4%BC%98%E7%A7%80%E8%BD%AF%E4%BB%B6%E6%8E%A8%E8%8D%90/img14.png\"></p>\n<h3 id=\"PotPlayer\"><a href=\"#PotPlayer\" class=\"headerlink\" title=\"PotPlayer\"></a>PotPlayer</h3><p>官网：<a href=\"https://potplayer.tv/?lang=zh_CN\">https://potplayer.tv/?lang=zh_CN</a> </p>\n<ul>\n<li><p><input disabled=\"\" type=\"checkbox\"> \n免安装</p>\n</li>\n<li><p><input disabled=\"\" type=\"checkbox\"> \n开源</p>\n</li>\n<li><p><input checked=\"\" disabled=\"\" type=\"checkbox\"> \n有官网</p>\n</li>\n<li><p><input checked=\"\" disabled=\"\" type=\"checkbox\"> \n连接快</p>\n</li>\n<li><p><input checked=\"\" disabled=\"\" type=\"checkbox\"> \n免费</p>\n</li>\n<li><p><input checked=\"\" disabled=\"\" type=\"checkbox\"> \n操作简单</p>\n</li>\n<li><p><input checked=\"\" disabled=\"\" type=\"checkbox\"> \n中文支持</p>\n</li>\n</ul>\n<p>内置了 FFmpeg，地表最强（吗？）的音视频播放器。</p>\n<p>并没有图片这么简陋。</p>\n<p><img src=\"/assets/%E4%BC%98%E7%A7%80%E8%BD%AF%E4%BB%B6%E6%8E%A8%E8%8D%90/img16.png\"></p>\n<h3 id=\"LocalSend\"><a href=\"#LocalSend\" class=\"headerlink\" title=\"LocalSend\"></a>LocalSend</h3><p>官网：<a href=\"https://localsend.org/zh-CN\">https://localsend.org/zh-CN</a> </p>\n<p>仓库：<a href=\"https://github.com/localsend/localsend\">https://github.com/localsend/localsend</a> </p>\n<p>支持 MacOS, Linux, Android, iOS</p>\n<ul>\n<li><p><input checked=\"\" disabled=\"\" type=\"checkbox\"> \n免安装</p>\n</li>\n<li><p><input checked=\"\" disabled=\"\" type=\"checkbox\"> \n开源</p>\n</li>\n<li><p><input checked=\"\" disabled=\"\" type=\"checkbox\"> \n有官网</p>\n</li>\n<li><p><input checked=\"\" disabled=\"\" type=\"checkbox\"> \n连接快</p>\n</li>\n<li><p><input checked=\"\" disabled=\"\" type=\"checkbox\"> \n免费</p>\n</li>\n<li><p><input checked=\"\" disabled=\"\" type=\"checkbox\"> \n操作简单</p>\n</li>\n<li><p><input checked=\"\" disabled=\"\" type=\"checkbox\"> \n中文支持</p>\n</li>\n</ul>\n<p>快速在设备间传输文件、媒体、软件。可通过软件（快速）、链接（某一方没有这个软件）分享。</p>\n<p><img src=\"/assets/%E4%BC%98%E7%A7%80%E8%BD%AF%E4%BB%B6%E6%8E%A8%E8%8D%90/img17.png\"></p>\n<h3 id=\"M3U8-Downloader\"><a href=\"#M3U8-Downloader\" class=\"headerlink\" title=\"M3U8-Downloader\"></a>M3U8-Downloader</h3><p>仓库：<a href=\"https://github.com/HeiSir2014/M3U8-Downloader\">https://github.com/HeiSir2014/M3U8-Downloader</a> </p>\n<ul>\n<li><p><input disabled=\"\" type=\"checkbox\"> \n免安装</p>\n</li>\n<li><p><input checked=\"\" disabled=\"\" type=\"checkbox\"> \n开源</p>\n</li>\n<li><p><input disabled=\"\" type=\"checkbox\"> \n有官网</p>\n</li>\n<li><p><input disabled=\"\" type=\"checkbox\"> \n连接快</p>\n</li>\n<li><p><input checked=\"\" disabled=\"\" type=\"checkbox\"> \n免费</p>\n</li>\n<li><p><input checked=\"\" disabled=\"\" type=\"checkbox\"> \n操作简单</p>\n</li>\n<li><p><input checked=\"\" disabled=\"\" type=\"checkbox\"> \n中文支持</p>\n</li>\n</ul>\n<p>将 m3u8 下载为 mp4，支持 ts 视频片段合并为 mp4。</p>\n<p>截止到目前，上个月更新了一次，但官网早就没了。</p>\n<p><img src=\"/assets/%E4%BC%98%E7%A7%80%E8%BD%AF%E4%BB%B6%E6%8E%A8%E8%8D%90/img18.png\"></p>\n<h3 id=\"Mem-Reduct\"><a href=\"#Mem-Reduct\" class=\"headerlink\" title=\"Mem Reduct\"></a>Mem Reduct</h3><p>官网：<a href=\"https://memreduct.org/\">https://memreduct.org</a> </p>\n<p>仓库：<a href=\"https://github.com/henrypp/memreduct\">https://github.com/henrypp/memreduct</a> </p>\n<ul>\n<li><p><input checked=\"\" disabled=\"\" type=\"checkbox\"> \n免安装</p>\n</li>\n<li><p><input checked=\"\" disabled=\"\" type=\"checkbox\"> \n开源</p>\n</li>\n<li><p><input checked=\"\" disabled=\"\" type=\"checkbox\"> \n有官网</p>\n</li>\n<li><p><input checked=\"\" disabled=\"\" type=\"checkbox\"> \n连接快</p>\n</li>\n<li><p><input checked=\"\" disabled=\"\" type=\"checkbox\"> \n免费</p>\n</li>\n<li><p><input checked=\"\" disabled=\"\" type=\"checkbox\"> \n操作简单</p>\n</li>\n<li><p><input checked=\"\" disabled=\"\" type=\"checkbox\"> \n中文支持</p>\n</li>\n</ul>\n<p>内存清理工具，将物理内存移到虚拟内存。</p>\n<p><img src=\"/assets/%E4%BC%98%E7%A7%80%E8%BD%AF%E4%BB%B6%E6%8E%A8%E8%8D%90/img19.png\"></p>\n<h3 id=\"VSCode\"><a href=\"#VSCode\" class=\"headerlink\" title=\"VSCode\"></a>VSCode</h3><p>官网：<a href=\"https://code.visualstudio.com/\">https://code.visualstudio.com/</a> </p>\n<p>仓库：<a href=\"https://github.com/microsoft/vscode\">https://github.com/microsoft/vscode</a> </p>\n<p>支持 MacOS, Linux</p>\n<ul>\n<li><p><input disabled=\"\" type=\"checkbox\"> \n免安装</p>\n</li>\n<li><p><input checked=\"\" disabled=\"\" type=\"checkbox\"> \n开源</p>\n</li>\n<li><p><input checked=\"\" disabled=\"\" type=\"checkbox\"> \n有官网</p>\n</li>\n<li><p><input checked=\"\" disabled=\"\" type=\"checkbox\"> \n连接快</p>\n</li>\n<li><p><input checked=\"\" disabled=\"\" type=\"checkbox\"> \n免费</p>\n</li>\n<li><p><input disabled=\"\" type=\"checkbox\"> \n操作简单</p>\n</li>\n<li><p><input disabled=\"\" type=\"checkbox\"> \n中文支持</p>\n</li>\n</ul>\n<p>微软出品文本编辑器，扩展市场庞大，安装插件后变身 IDE。</p>\n<p>可安装汉化扩展。</p>\n<p><img src=\"/assets/%E4%BC%98%E7%A7%80%E8%BD%AF%E4%BB%B6%E6%8E%A8%E8%8D%90/img20.png\"></p>\n<h3 id=\"Watt-Toolkit\"><a href=\"#Watt-Toolkit\" class=\"headerlink\" title=\"Watt Toolkit\"></a>Watt Toolkit</h3><p>官网：<a href=\"https://steampp.net/\">https://steampp.net/</a> </p>\n<p>仓库：<a href=\"https://github.com/BeyondDimension/SteamTools\">https://github.com/BeyondDimension/SteamTools</a> </p>\n<p>支持 MacOS, Linux</p>\n<ul>\n<li><p><input disabled=\"\" type=\"checkbox\"> \n免安装</p>\n</li>\n<li><p><input checked=\"\" disabled=\"\" type=\"checkbox\"> \n开源</p>\n</li>\n<li><p><input checked=\"\" disabled=\"\" type=\"checkbox\"> \n有官网</p>\n</li>\n<li><p><input checked=\"\" disabled=\"\" type=\"checkbox\"> \n连接快</p>\n</li>\n<li><p><input checked=\"\" disabled=\"\" type=\"checkbox\"> \n免费</p>\n</li>\n<li><p><input checked=\"\" disabled=\"\" type=\"checkbox\"> \n操作简单</p>\n</li>\n<li><p><input checked=\"\" disabled=\"\" type=\"checkbox\"> \n中文支持</p>\n</li>\n</ul>\n<p>加速器（原名 Steam++），可以加速 github, steam，也包括部分海外网站应用。</p>\n<p><img src=\"/assets/%E4%BC%98%E7%A7%80%E8%BD%AF%E4%BB%B6%E6%8E%A8%E8%8D%90/img21.png\"></p>\n<h3 id=\"Subtitle-Edit\"><a href=\"#Subtitle-Edit\" class=\"headerlink\" title=\"Subtitle Edit\"></a>Subtitle Edit</h3><p>官网：<a href=\"https://www.nikse.dk/subtitleedit\">https://www.nikse.dk/subtitleedit</a> </p>\n<p>仓库：<a href=\"https://github.com/SubtitleEdit/subtitleedit\">https://github.com/SubtitleEdit/subtitleedit</a> </p>\n<ul>\n<li><p><input checked=\"\" disabled=\"\" type=\"checkbox\"> \n免安装</p>\n</li>\n<li><p><input checked=\"\" disabled=\"\" type=\"checkbox\"> \n开源</p>\n</li>\n<li><p><input checked=\"\" disabled=\"\" type=\"checkbox\"> \n有官网</p>\n</li>\n<li><p><input disabled=\"\" type=\"checkbox\"> \n连接快</p>\n</li>\n<li><p><input checked=\"\" disabled=\"\" type=\"checkbox\"> \n免费</p>\n</li>\n<li><p><input checked=\"\" disabled=\"\" type=\"checkbox\"> \n操作简单</p>\n</li>\n<li><p><input checked=\"\" disabled=\"\" type=\"checkbox\"> \n中文支持</p>\n</li>\n</ul>\n<p>字幕编辑软件，支持多种字幕格式。</p>\n<p><img src=\"/assets/%E4%BC%98%E7%A7%80%E8%BD%AF%E4%BB%B6%E6%8E%A8%E8%8D%90/img22.png\"></p>\n<h3 id=\"Internet-Download-Manager\"><a href=\"#Internet-Download-Manager\" class=\"headerlink\" title=\"Internet Download Manager\"></a>Internet Download Manager</h3><p>官网：<a href=\"https://www.internetdownloadmanager.com/\">https://www.internetdownloadmanager.com/</a> </p>\n<ul>\n<li><p><input disabled=\"\" type=\"checkbox\"> \n免安装</p>\n</li>\n<li><p><input disabled=\"\" type=\"checkbox\"> \n开源</p>\n</li>\n<li><p><input checked=\"\" disabled=\"\" type=\"checkbox\"> \n有官网</p>\n</li>\n<li><p><input checked=\"\" disabled=\"\" type=\"checkbox\"> \n连接快</p>\n</li>\n<li><p><input disabled=\"\" type=\"checkbox\"> \n免费</p>\n</li>\n<li><p><input checked=\"\" disabled=\"\" type=\"checkbox\"> \n操作简单</p>\n</li>\n<li><p><input checked=\"\" disabled=\"\" type=\"checkbox\"> \n中文支持</p>\n</li>\n</ul>\n<p><strong>可试用 30 天。</strong></p>\n<p><img src=\"/assets/%E4%BC%98%E7%A7%80%E8%BD%AF%E4%BB%B6%E6%8E%A8%E8%8D%90/img23.png\"></p>\n<p>高速多线程下载器，可拉满带宽。</p>\n<p><img src=\"/assets/%E4%BC%98%E7%A7%80%E8%BD%AF%E4%BB%B6%E6%8E%A8%E8%8D%90/img24.png\"></p>\n<h3 id=\"RayLink\"><a href=\"#RayLink\" class=\"headerlink\" title=\"RayLink\"></a>RayLink</h3><p>官网：<a href=\"https://www.raylink.live/\">https://www.raylink.live/</a> </p>\n<p>支持 MacOS, Linux, Android, iOS, Web</p>\n<ul>\n<li><p><input disabled=\"\" type=\"checkbox\"> \n免安装</p>\n</li>\n<li><p><input disabled=\"\" type=\"checkbox\"> \n开源</p>\n</li>\n<li><p><input checked=\"\" disabled=\"\" type=\"checkbox\"> \n有官网</p>\n</li>\n<li><p><input checked=\"\" disabled=\"\" type=\"checkbox\"> \n连接快</p>\n</li>\n<li><p><input checked=\"\" disabled=\"\" type=\"checkbox\"> \n免费</p>\n</li>\n<li><p><input checked=\"\" disabled=\"\" type=\"checkbox\"> \n操作简单</p>\n</li>\n<li><p><input checked=\"\" disabled=\"\" type=\"checkbox\"> \n中文支持</p>\n</li>\n</ul>\n<p><img src=\"/assets/%E4%BC%98%E7%A7%80%E8%BD%AF%E4%BB%B6%E6%8E%A8%E8%8D%90/img26.png\"></p>\n<p>手机远控电脑。收费项目比 ToDesk 少。</p>\n<p><img src=\"/assets/%E4%BC%98%E7%A7%80%E8%BD%AF%E4%BB%B6%E6%8E%A8%E8%8D%90/img25.png\"></p>\n<h3 id=\"Windows-Cleaner\"><a href=\"#Windows-Cleaner\" class=\"headerlink\" title=\"Windows Cleaner\"></a>Windows Cleaner</h3><p>官网：<a href=\"https://wc.dyblog.online/\">https://wc.dyblog.online/</a> </p>\n<p>仓库：<a href=\"https://github.com/darkmatter2048/WindowsCleaner\">https://github.com/darkmatter2048/WindowsCleaner</a> </p>\n<ul>\n<li><p><input disabled=\"\" type=\"checkbox\"> \n免安装</p>\n</li>\n<li><p><input checked=\"\" disabled=\"\" type=\"checkbox\"> \n开源</p>\n</li>\n<li><p><input checked=\"\" disabled=\"\" type=\"checkbox\"> \n有官网</p>\n</li>\n<li><p><input checked=\"\" disabled=\"\" type=\"checkbox\"> \n连接快</p>\n</li>\n<li><p><input checked=\"\" disabled=\"\" type=\"checkbox\"> \n免费</p>\n</li>\n<li><p><input checked=\"\" disabled=\"\" type=\"checkbox\"> \n操作简单</p>\n</li>\n<li><p><input checked=\"\" disabled=\"\" type=\"checkbox\"> \n中文支持</p>\n</li>\n</ul>\n<p>清理 Windows 储存的工具，比磁盘清理好。</p>\n<p><img src=\"/assets/%E4%BC%98%E7%A7%80%E8%BD%AF%E4%BB%B6%E6%8E%A8%E8%8D%90/img27.png\"></p>\n<h3 id=\"dev-sidecar\"><a href=\"#dev-sidecar\" class=\"headerlink\" title=\"dev-sidecar\"></a>dev-sidecar</h3><p>仓库：<a href=\"https://github.com/docmirror/dev-sidecar\">https://github.com/docmirror/dev-sidecar</a> </p>\n<ul>\n<li><p><input disabled=\"\" type=\"checkbox\"> \n免安装</p>\n</li>\n<li><p><input checked=\"\" disabled=\"\" type=\"checkbox\"> \n开源</p>\n</li>\n<li><p><input disabled=\"\" type=\"checkbox\"> \n有官网</p>\n</li>\n<li><p><input disabled=\"\" type=\"checkbox\"> \n连接快</p>\n</li>\n<li><p><input checked=\"\" disabled=\"\" type=\"checkbox\"> \n免费</p>\n</li>\n<li><p><input checked=\"\" disabled=\"\" type=\"checkbox\"> \n操作简单</p>\n</li>\n<li><p><input checked=\"\" disabled=\"\" type=\"checkbox\"> \n中文支持</p>\n</li>\n</ul>\n<p>代理工具，可加速 github。</p>\n<p><img src=\"/assets/%E4%BC%98%E7%A7%80%E8%BD%AF%E4%BB%B6%E6%8E%A8%E8%8D%90/img28.png\"></p>\n<h2 id=\"较为推荐\"><a href=\"#较为推荐\" class=\"headerlink\" title=\"较为推荐\"></a>较为推荐</h2><h3 id=\"DiskGenius\"><a href=\"#DiskGenius\" class=\"headerlink\" title=\"DiskGenius\"></a>DiskGenius</h3><p>官网：<a href=\"https://www.diskgenius.cn/\">https://www.diskgenius.cn/</a> </p>\n<ul>\n<li><p><input checked=\"\" disabled=\"\" type=\"checkbox\"> \n免安装</p>\n</li>\n<li><p><input disabled=\"\" type=\"checkbox\"> \n开源</p>\n</li>\n<li><p><input checked=\"\" disabled=\"\" type=\"checkbox\"> \n有官网</p>\n</li>\n<li><p><input checked=\"\" disabled=\"\" type=\"checkbox\"> \n连接快</p>\n</li>\n<li><p><input checked=\"\" disabled=\"\" type=\"checkbox\"> \n免费</p>\n</li>\n<li><p><input disabled=\"\" type=\"checkbox\"> \n操作简单</p>\n</li>\n<li><p><input checked=\"\" disabled=\"\" type=\"checkbox\"> \n中文支持</p>\n</li>\n</ul>\n<p><strong>高级功能需付费。</strong></p>\n<p><img src=\"/assets/%E4%BC%98%E7%A7%80%E8%BD%AF%E4%BB%B6%E6%8E%A8%E8%8D%90/img4.png\"></p>\n<p>专业的数据恢复软件，支持各种情况下的文件恢复和分区恢复，恢复效果好，包括各种硬盘操作。</p>\n<p><mark><em><strong><u>不要轻易尝试！！！一定要让专业人士使用！！！若操作不当所产生严重后果，一切与我无关，我不承担任何责任！！！</u></strong></em></mark></p>\n<h3 id=\"Dism\"><a href=\"#Dism\" class=\"headerlink\" title=\"Dism++\"></a>Dism++</h3><p>仓库：<a href=\"https://github.com/Chuyu-Team/Dism-Multi-language\">https://github.com/Chuyu-Team/Dism-Multi-language</a> </p>\n<ul>\n<li><p><input checked=\"\" disabled=\"\" type=\"checkbox\"> \n免安装</p>\n</li>\n<li><p><input checked=\"\" disabled=\"\" type=\"checkbox\"> \n开源</p>\n</li>\n<li><p><input disabled=\"\" type=\"checkbox\"> \n有官网</p>\n</li>\n<li><p><input disabled=\"\" type=\"checkbox\"> \n连接快</p>\n</li>\n<li><p><input checked=\"\" disabled=\"\" type=\"checkbox\"> \n免费</p>\n</li>\n<li><p><input checked=\"\" disabled=\"\" type=\"checkbox\"> \n操作简单</p>\n</li>\n<li><p><input checked=\"\" disabled=\"\" type=\"checkbox\"> \n中文支持</p>\n</li>\n</ul>\n<p>一个 Windows 系统管理优化工具。</p>\n<p><mark><em><strong><u>部分功能不要轻易尝试！！！</u></strong></em></mark></p>\n<p><img src=\"/assets/%E4%BC%98%E7%A7%80%E8%BD%AF%E4%BB%B6%E6%8E%A8%E8%8D%90/img6.png\"></p>\n<h3 id=\"FFmpeg\"><a href=\"#FFmpeg\" class=\"headerlink\" title=\"FFmpeg\"></a>FFmpeg</h3><p>官网：<a href=\"https://ffmpeg.org/\">https://ffmpeg.org/</a> </p>\n<p>仓库：<a href=\"https://github.com/FFmpeg/FFmpeg\">https://github.com/FFmpeg/FFmpeg</a> </p>\n<p>支持 MacOS, Linux</p>\n<ul>\n<li><p><input checked=\"\" disabled=\"\" type=\"checkbox\"> \n免安装</p>\n</li>\n<li><p><input checked=\"\" disabled=\"\" type=\"checkbox\"> \n开源</p>\n</li>\n<li><p><input checked=\"\" disabled=\"\" type=\"checkbox\"> \n有官网</p>\n</li>\n<li><p><input checked=\"\" disabled=\"\" type=\"checkbox\"> \n连接快</p>\n</li>\n<li><p><input checked=\"\" disabled=\"\" type=\"checkbox\"> \n免费</p>\n</li>\n<li><p><input disabled=\"\" type=\"checkbox\"> \n操作简单</p>\n</li>\n<li><p><input disabled=\"\" type=\"checkbox\"> \n中文支持</p>\n</li>\n</ul>\n<p>最（吗？）万能的音视频处理器（不是硬件那个“处理器”），基本上与音视频有关的软件都和 FFmpeg 有关。FFmpeg 可以快速实现格式转换，也可以播放视频（甚至有人用它做出了动态壁纸）。</p>\n<p>FFmpeg 只能通过命令行操作。</p>\n<h2 id=\"可以试试\"><a href=\"#可以试试\" class=\"headerlink\" title=\"可以试试\"></a>可以试试</h2><h3 id=\"BoosterX\"><a href=\"#BoosterX\" class=\"headerlink\" title=\"BoosterX\"></a>BoosterX</h3><p>官网：<a href=\"https://boosterx.org/zh/\">https://boosterx.org/zh/</a> </p>\n<p>仓库：<a href=\"https://github.com/MrSanZz/BoosterX\">https://github.com/MrSanZz/BoosterX</a> </p>\n<ul>\n<li><p><input checked=\"\" disabled=\"\" type=\"checkbox\"> \n免安装</p>\n</li>\n<li><p><input checked=\"\" disabled=\"\" type=\"checkbox\"> \n开源</p>\n</li>\n<li><p><input checked=\"\" disabled=\"\" type=\"checkbox\"> \n有官网</p>\n</li>\n<li><p><input disabled=\"\" type=\"checkbox\"> \n连接快</p>\n</li>\n<li><p><input checked=\"\" disabled=\"\" type=\"checkbox\"> \n免费</p>\n</li>\n<li><p><input checked=\"\" disabled=\"\" type=\"checkbox\"> \n操作简单</p>\n</li>\n<li><p><input checked=\"\" disabled=\"\" type=\"checkbox\"> \n中文支持</p>\n</li>\n</ul>\n<p>Windows 系统优化工具，可以砍掉很多功能。</p>\n<p><strong>高级功能需付费</strong>。（我无法连接，不能给出价格）</p>\n<p><img src=\"/assets/%E4%BC%98%E7%A7%80%E8%BD%AF%E4%BB%B6%E6%8E%A8%E8%8D%90/img11.png\"></p>\n<h3 id=\"搞机工具箱\"><a href=\"#搞机工具箱\" class=\"headerlink\" title=\"搞机工具箱\"></a>搞机工具箱</h3><p>官网：<a href=\"https://www.jamcz.com/gjgjx/\">https://www.jamcz.com/gjgjx/</a> </p>\n<ul>\n<li><p><input checked=\"\" disabled=\"\" type=\"checkbox\"> \n免安装</p>\n</li>\n<li><p><input disabled=\"\" type=\"checkbox\"> \n开源</p>\n</li>\n<li><p><input checked=\"\" disabled=\"\" type=\"checkbox\"> \n有官网</p>\n</li>\n<li><p><input checked=\"\" disabled=\"\" type=\"checkbox\"> \n连接快</p>\n</li>\n<li><p><input checked=\"\" disabled=\"\" type=\"checkbox\"> \n免费</p>\n</li>\n<li><p><input checked=\"\" disabled=\"\" type=\"checkbox\"> \n操作简单</p>\n</li>\n<li><p><input checked=\"\" disabled=\"\" type=\"checkbox\"> \n中文支持</p>\n</li>\n</ul>\n<p>无需 ROOT 即可管理手机。</p>\n<p><mark><em><strong><u>不要轻易尝试！！！</u></strong></em></mark></p>\n<p><img src=\"/assets/%E4%BC%98%E7%A7%80%E8%BD%AF%E4%BB%B6%E6%8E%A8%E8%8D%90/img15.png\"></p>\n","feature":true,"text":"优秀软件推荐如无特殊说明，默认仅支持 Windows。“免费”指基本功能，如有收费内容会说明。“连接快”指任一下载页面访问快。（如经常断连则不会勾选） 本帖并无...","permalink":"/post/优秀软件推荐","photos":[],"count_time":{"symbolsCount":"4.8k","symbolsTime":"4 mins."},"categories":[],"tags":[],"toc":"<ol class=\"toc\"><li class=\"toc-item toc-level-1\"><a class=\"toc-link\" href=\"#%E4%BC%98%E7%A7%80%E8%BD%AF%E4%BB%B6%E6%8E%A8%E8%8D%90\"><span class=\"toc-text\">优秀软件推荐</span></a><ol class=\"toc-child\"><li class=\"toc-item toc-level-2\"><a class=\"toc-link\" href=\"#%E5%BC%BA%E7%83%88%E6%8E%A8%E8%8D%90\"><span class=\"toc-text\">强烈推荐</span></a><ol class=\"toc-child\"><li class=\"toc-item toc-level-3\"><a class=\"toc-link\" href=\"#163MusicLyrics\"><span class=\"toc-text\">163MusicLyrics</span></a></li><li class=\"toc-item toc-level-3\"><a class=\"toc-link\" href=\"#ApkShellext2\"><span class=\"toc-text\">ApkShellext2</span></a></li><li class=\"toc-item toc-level-3\"><a class=\"toc-link\" href=\"#Bandicam\"><span class=\"toc-text\">Bandicam</span></a></li><li class=\"toc-item toc-level-3\"><a class=\"toc-link\" href=\"#DirectX-Repair\"><span class=\"toc-text\">DirectX_Repair</span></a></li><li class=\"toc-item toc-level-3\"><a class=\"toc-link\" href=\"#MarkText\"><span class=\"toc-text\">MarkText</span></a></li><li class=\"toc-item toc-level-3\"><a class=\"toc-link\" href=\"#noMeiryoUI\"><span class=\"toc-text\">noMeiryoUI</span></a></li><li class=\"toc-item toc-level-3\"><a class=\"toc-link\" href=\"#Office-Tool\"><span class=\"toc-text\">Office Tool</span></a></li><li class=\"toc-item toc-level-3\"><a class=\"toc-link\" href=\"#QtScrcpy\"><span class=\"toc-text\">QtScrcpy</span></a></li><li class=\"toc-item toc-level-3\"><a class=\"toc-link\" href=\"#Windows-%E5%8F%B3%E9%94%AE%E7%AE%A1%E7%90%86\"><span class=\"toc-text\">Windows 右键管理</span></a></li><li class=\"toc-item toc-level-3\"><a class=\"toc-link\" href=\"#Resourse-Hacker\"><span class=\"toc-text\">Resourse Hacker</span></a></li><li class=\"toc-item toc-level-3\"><a class=\"toc-link\" href=\"#Geek-Uninstaller\"><span class=\"toc-text\">Geek Uninstaller</span></a></li><li class=\"toc-item toc-level-3\"><a class=\"toc-link\" href=\"#PotPlayer\"><span class=\"toc-text\">PotPlayer</span></a></li><li class=\"toc-item toc-level-3\"><a class=\"toc-link\" href=\"#LocalSend\"><span class=\"toc-text\">LocalSend</span></a></li><li class=\"toc-item toc-level-3\"><a class=\"toc-link\" href=\"#M3U8-Downloader\"><span class=\"toc-text\">M3U8-Downloader</span></a></li><li class=\"toc-item toc-level-3\"><a class=\"toc-link\" href=\"#Mem-Reduct\"><span class=\"toc-text\">Mem Reduct</span></a></li><li class=\"toc-item toc-level-3\"><a class=\"toc-link\" href=\"#VSCode\"><span class=\"toc-text\">VSCode</span></a></li><li class=\"toc-item toc-level-3\"><a class=\"toc-link\" href=\"#Watt-Toolkit\"><span class=\"toc-text\">Watt Toolkit</span></a></li><li class=\"toc-item toc-level-3\"><a class=\"toc-link\" href=\"#Subtitle-Edit\"><span class=\"toc-text\">Subtitle Edit</span></a></li><li class=\"toc-item toc-level-3\"><a class=\"toc-link\" href=\"#Internet-Download-Manager\"><span class=\"toc-text\">Internet Download Manager</span></a></li><li class=\"toc-item toc-level-3\"><a class=\"toc-link\" href=\"#RayLink\"><span class=\"toc-text\">RayLink</span></a></li><li class=\"toc-item toc-level-3\"><a class=\"toc-link\" href=\"#Windows-Cleaner\"><span class=\"toc-text\">Windows Cleaner</span></a></li><li class=\"toc-item toc-level-3\"><a class=\"toc-link\" href=\"#dev-sidecar\"><span class=\"toc-text\">dev-sidecar</span></a></li></ol></li><li class=\"toc-item toc-level-2\"><a class=\"toc-link\" href=\"#%E8%BE%83%E4%B8%BA%E6%8E%A8%E8%8D%90\"><span class=\"toc-text\">较为推荐</span></a><ol class=\"toc-child\"><li class=\"toc-item toc-level-3\"><a class=\"toc-link\" href=\"#DiskGenius\"><span class=\"toc-text\">DiskGenius</span></a></li><li class=\"toc-item toc-level-3\"><a class=\"toc-link\" href=\"#Dism\"><span class=\"toc-text\">Dism++</span></a></li><li class=\"toc-item toc-level-3\"><a class=\"toc-link\" href=\"#FFmpeg\"><span class=\"toc-text\">FFmpeg</span></a></li></ol></li><li class=\"toc-item toc-level-2\"><a class=\"toc-link\" href=\"#%E5%8F%AF%E4%BB%A5%E8%AF%95%E8%AF%95\"><span class=\"toc-text\">可以试试</span></a><ol class=\"toc-child\"><li class=\"toc-item toc-level-3\"><a class=\"toc-link\" href=\"#BoosterX\"><span class=\"toc-text\">BoosterX</span></a></li><li class=\"toc-item toc-level-3\"><a class=\"toc-link\" href=\"#%E6%90%9E%E6%9C%BA%E5%B7%A5%E5%85%B7%E7%AE%B1\"><span class=\"toc-text\">搞机工具箱</span></a></li></ol></li></ol></li></ol>","author":{"name":"ling-314","slug":"blog-author","avatar":"/icons/avatar.jpg","link":"/","description":"初中牲的日常","socials":{"github":"https://github.com/ling-314","twitter":"","stackoverflow":"","wechat":"","qq":"","weibo":"","zhihu":"","csdn":"","juejin":"","customs":{"bilibili":{"icon":"/icons/bilibili.svg","link":"https://space.bilibili.com/1405802918"},"QQ":{"icon":"/icons/qq.svg","link":"https://qm.qq.com/q/PM3T5CPtwy"}}}},"mapped":true,"hidden":false,"prev_post":{"title":"断网也能救","uid":"dd2d027d1184dae96513e18df910baef","slug":"断网也能救","date":"2025-06-29T05:24:39.000Z","updated":"2025-06-29T05:25:49.441Z","comments":true,"path":"api/articles/断网也能救.json","keywords":"编程 日常 游戏","cover":[],"text":"断网也能救这里所说的『断网』指设备被加入路由器黑名单导致的设备无法访问 Internet。 原理如果你进入过路由器后台，可能会在黑/白名单中看见一些由数字、字母...","permalink":"/post/断网也能救","photos":[],"count_time":{"symbolsCount":"1.2k","symbolsTime":"1 mins."},"categories":[],"tags":[{"name":"网络","slug":"网络","count":1,"path":"api/tags/网络.json"}],"author":{"name":"ling-314","slug":"blog-author","avatar":"/icons/avatar.jpg","link":"/","description":"初中牲的日常","socials":{"github":"https://github.com/ling-314","twitter":"","stackoverflow":"","wechat":"","qq":"","weibo":"","zhihu":"","csdn":"","juejin":"","customs":{"bilibili":{"icon":"/icons/bilibili.svg","link":"https://space.bilibili.com/1405802918"},"QQ":{"icon":"/icons/qq.svg","link":"https://qm.qq.com/q/PM3T5CPtwy"}}}},"feature":true},"next_post":{"title":"Markdown 发布更好的教程","uid":"65d17389bd3699356a25c16b664f62f4","slug":"Markdown-发布更好的教程","date":"2025-06-29T05:10:58.000Z","updated":"2025-06-29T05:22:07.915Z","comments":true,"path":"api/articles/Markdown-发布更好的教程.json","keywords":"编程 日常 游戏","cover":[],"text":"Markdown 发布更好的教程随着几年前 BCM 在论坛加入了“训练师小课堂”板块，各种教程层出不穷。但 BCM 的帖子编辑器功能较少，不能满足部分需求，并且...","permalink":"/post/Markdown-发布更好的教程","photos":[],"count_time":{"symbolsCount":"2.1k","symbolsTime":"2 mins."},"categories":[],"tags":[{"name":"Makrdown","slug":"Makrdown","count":1,"path":"api/tags/Makrdown.json"},{"name":"VSCode","slug":"VSCode","count":1,"path":"api/tags/VSCode.json"}],"author":{"name":"ling-314","slug":"blog-author","avatar":"/icons/avatar.jpg","link":"/","description":"初中牲的日常","socials":{"github":"https://github.com/ling-314","twitter":"","stackoverflow":"","wechat":"","qq":"","weibo":"","zhihu":"","csdn":"","juejin":"","customs":{"bilibili":{"icon":"/icons/bilibili.svg","link":"https://space.bilibili.com/1405802918"},"QQ":{"icon":"/icons/qq.svg","link":"https://qm.qq.com/q/PM3T5CPtwy"}}}},"feature":true}}