{"name":"Kitten4","slug":"Kitten4","count":1,"postlist":[{"title":"K4作品文件解剖","uid":"333cbe4c4352177cf877fa37036a47fe","slug":"K4作品文件解剖","date":"2025-06-29T05:06:44.000Z","updated":"2025-06-29T05:17:31.815Z","comments":true,"path":"api/articles/K4作品文件解剖.json","keywords":"编程 日常 游戏","cover":[],"text":"提示：本帖内容非常硬核，建议有计算机基础的人观看 K4作品文件解剖前言我们每创建一个K4作品，编程猫都会生成一个对应的.bcm4文件来储存作品的信息，对作品的每...","permalink":"/post/K4作品文件解剖","photos":[],"count_time":{"symbolsCount":"4.4k","symbolsTime":"4 mins."},"categories":[],"tags":[{"name":"编程猫","slug":"编程猫","count":3,"path":"api/tags/编程猫.json"},{"name":"Kitten4","slug":"Kitten4","count":1,"path":"api/tags/Kitten4.json"}],"author":{"name":"ling-314","slug":"blog-author","avatar":"/icons/avatar.jpg","link":"/","description":"初中牲的日常","socials":{"github":"https://github.com/ling-314","twitter":"","stackoverflow":"","wechat":"","qq":"","weibo":"","zhihu":"","csdn":"","juejin":"","customs":{"bilibili":{"icon":"/icons/bilibili.svg","link":"https://space.bilibili.com/1405802918"},"QQ":{"icon":"/icons/qq.svg","link":"https://qm.qq.com/q/PM3T5CPtwy"}}}}}]}